[
    {
        "title": "Power your life",
        "description": "Find out about how to click buttons to empower your life.",
        "buttonLabel": "Click here",
        "imageUrl": "assets/images/diet.png",
        "link": "/page2",
        "type": "internal",
        "category": "Food"
    },
    {
        "title": "Power your life",
        "description": "Find out about how to click buttons to empower your life.",
        "buttonLabel": "Click here",
        "imageUrl": "assets/images/diet.png",
        "link": "/page2",
        "type": "internal",
        "category": "Health"
    },
    {
        "title": "Power your life",
        "description": "Find out about how to click buttons to empower your life.",
        "buttonLabel": "Click here",
        "imageUrl": "assets/images/diet.png",
        "link": "/page2",
        "type": "external",
        "category": "Shopping"
    },
    {
        "title": "Power your life",
        "description": "Find out about how to click buttons to empower your life.",
        "buttonLabel": "Click here",
        "imageUrl": "assets/images/diet.png",
        "link": "/page2",
        "type": "external",
        "category": "Music"
    }
]